specifications/__init__.py
specifications/admin.py
specifications/forms.py
specifications/models.py
specifications/utils.py
specifications/locale/de/LC_MESSAGES/django.mo
specifications/locale/de/LC_MESSAGES/django.po
specifications/migrations/0001_initial.py
specifications/migrations/__init__.py
specifications/templates/admin/specifications/specification/change_form.html
django_specifications-0.5.0.dist-info/LICENSE
django_specifications-0.5.0.dist-info/METADATA
django_specifications-0.5.0.dist-info/WHEEL
django_specifications-0.5.0.dist-info/top_level.txt
django_specifications-0.5.0.dist-info/RECORD
