Metadata-Version: 2.1
Name: django-specifications
Version: 0.5.0
Summary: Additional, dynamic fields for all Django models.
Home-page: https://github.com/matthiask/django-specifications/
Author: Matthias Kestenholz
Author-email: mk@feinheit.ch
License: BSD-3-Clause
Platform: OS Independent
Classifier: Development Status :: 5 - Production/Stable
Classifier: Environment :: Web Environment
Classifier: Framework :: Django
Classifier: Intended Audience :: Developers
Classifier: License :: OSI Approved :: BSD License
Classifier: Operating System :: OS Independent
Classifier: Programming Language :: Python
Classifier: Programming Language :: Python :: 3
Classifier: Programming Language :: Python :: 3 :: Only
Classifier: Programming Language :: Python :: 3.8
Classifier: Programming Language :: Python :: 3.9
Classifier: Topic :: Internet :: WWW/HTTP :: Dynamic Content
Classifier: Topic :: Software Development
Classifier: Topic :: Software Development :: Libraries :: Application Frameworks
Requires-Python: >=3.8
Requires-Dist: Django (>=3.2)
Provides-Extra: tests
Requires-Dist: coverage ; extra == 'tests'
